winremote/__init__.py
winremote/__main__.py
winremote/winremote.py
winremote/modules/__init__.py
winremote/modules/devices.py
winremote/modules/files.py
winremote/modules/products.py
winremote/modules/services.py
winremote/modules/system.py
winremote-1.1.3.dist-info/DESCRIPTION.rst
winremote-1.1.3.dist-info/METADATA
winremote-1.1.3.dist-info/RECORD
winremote-1.1.3.dist-info/WHEEL
winremote-1.1.3.dist-info/entry_points.txt
winremote-1.1.3.dist-info/metadata.json
winremote-1.1.3.dist-info/pbr.json
winremote-1.1.3.dist-info/top_level.txt
