Metadata-Version: 2.0
Name: winremote
Version: 1.1.3
Summary: Tool to manage your windows machines remotely
Home-page: https://github.com/machacekondra/winremote
Author: Ondra Machacek
Author-email: machacek.ondra@gmail.com
License: GPLv3+
Keywords: windows winrm
Platform: UNKNOWN
Classifier: Development Status :: 4 - Beta
Classifier: Intended Audience :: System Administrators
Classifier: Topic :: System :: Systems Administration
Classifier: License :: OSI Approved :: GNU General Public License v3 or later (GPLv3+)
Classifier: Programming Language :: Python :: 2
Classifier: Programming Language :: Python :: 2.6
Classifier: Programming Language :: Python :: 2.7
Classifier: Programming Language :: Python :: 3
Classifier: Programming Language :: Python :: 3.2
Classifier: Programming Language :: Python :: 3.3
Classifier: Programming Language :: Python :: 3.4
Requires-Dist: argparse
Requires-Dist: pypandoc
Requires-Dist: pywinrm
